{"../package.json":[],"binary/add.js":[],"binary/all.js":[],"binary/and.js":[],"binary/any.js":[],"binary/ap.js":[],"binary/apply.js":[],"binary/concat.js":[],"binary/cond.js":[],"binary/divide.js":[],"binary/equals.js":[],"binary/filter.js":[],"binary/find.js":[],"binary/forEach.js":[],"binary/gt.js":[],"binary/gte.js":[],"binary/includes.js":[],"binary/index-with-types.js":["binary/add.js","binary/all.js","binary/and.js","binary/any.js","binary/ap.js","binary/apply.js","binary/concat.js","binary/cond.js","binary/divide.js","binary/equals.js","binary/filter.js","binary/find.js","binary/forEach.js","binary/gt.js","binary/gte.js","binary/includes.js","binary/join.js","binary/lt.js","binary/lte.js","binary/map.js","binary/max.js","binary/min.js","binary/multiply.js","binary/nth.js","binary/or.js","binary/range.js","binary/sort.js","binary/split.js","binary/subtract.js","binary/toJSON.js"],"binary/index.js":["binary/add.js","binary/all.js","binary/and.js","binary/any.js","binary/ap.js","binary/apply.js","binary/concat.js","binary/cond.js","binary/divide.js","binary/equals.js","binary/filter.js","binary/find.js","binary/forEach.js","binary/gt.js","binary/gte.js","binary/includes.js","binary/join.js","binary/lt.js","binary/lte.js","binary/map.js","binary/max.js","binary/min.js","binary/multiply.js","binary/nth.js","binary/or.js","binary/range.js","binary/sort.js","binary/split.js","binary/subtract.js","binary/toJSON.js"],"binary/join.js":[],"binary/lt.js":[],"binary/lte.js":[],"binary/map.js":[],"binary/max.js":[],"binary/min.js":[],"binary/multiply.js":[],"binary/nth.js":[],"binary/or.js":[],"binary/range.js":[],"binary/sort.js":[],"binary/split.js":[],"binary/subtract.js":[],"binary/toJSON.js":[],"build/config.js":[],"build/core-with-types.js":["build/module.js"],"build/core.js":["build/module.js"],"build/debug.js":["build/config.js","build/core-with-types.js"],"build/module.js":[],"build/production.js":["build/config.js","build/core.js"],"build/tester.js":[],"core/F.js":[],"core/T.js":[],"core/adjust.js":[],"core/aliases.js":[],"core/append.js":[],"core/auto-curry.js":[],"core/box.js":[],"core/call.js":[],"core/complement.js":[],"core/constant.js":[],"core/constants.js":[],"core/dec.js":[],"core/first.js":[],"core/fromPairs.js":[],"core/identity.js":[],"core/inc.js":[],"core/index-with-types.js":["core/F.js","core/T.js","core/adjust.js","core/append.js","core/box.js","core/call.js","core/complement.js","core/constant.js","core/dec.js","core/first.js","core/fromPairs.js","core/identity.js","core/inc.js","core/init.js","core/jam.js","core/last.js","core/length.js","core/mash.js","core/mean.js","core/memoize-with.js","core/mode.js","core/native.js","core/not.js","core/pipe.js","core/prepend.js","core/reverse.js","core/smash.js","core/smooth.js","core/tail.js","core/temper.js","core/toLower.js","core/toPairs.js","core/toUpper.js","core/update.js"],"core/index.js":["core/F.js","core/T.js","core/adjust.js","core/append.js","core/box.js","core/call.js","core/complement.js","core/constant.js","core/dec.js","core/first.js","core/fromPairs.js","core/identity.js","core/inc.js","core/init.js","core/jam.js","core/last.js","core/length.js","core/mash.js","core/mean.js","core/mode.js","core/native.js","core/not.js","core/pipe.js","core/prepend.js","core/reverse.js","core/smash.js","core/smooth.js","core/tail.js","core/temper.js","core/toLower.js","core/toPairs.js","core/toUpper.js","core/update.js"],"core/init.js":[],"core/jam.js":[],"core/last.js":[],"core/length.js":[],"core/mash.js":[],"core/mean.js":[],"core/memoize-with.js":[],"core/mode.js":[],"core/native.js":[],"core/not.js":[],"core/pipe.js":[],"core/prepend.js":[],"core/reverse.js":[],"core/side-effect-with-types.js":[],"core/side-effect.js":[],"core/smash.js":[],"core/smooth.js":[],"core/tail.js":[],"core/temper.js":[],"core/toLower.js":[],"core/toPairs.js":[],"core/toUpper.js":[],"core/update.js":[],"derived/addIndex.js":[],"derived/bind.js":[],"derived/chain.js":[],"derived/difference.js":[],"derived/flatten.js":[],"derived/flip.js":[],"derived/ifElse-derivatives.js":[],"derived/index-with-types.js":["derived/addIndex.js","derived/bind.js","derived/chain.js","derived/difference.js","derived/flatten.js","derived/flip.js","derived/ifElse-derivatives.js","derived/isObject.js","derived/j2.js","derived/median.js","derived/pathOr-derivatives-with-types.js","derived/pathOr.js","derived/pluck.js","derived/predPass-with-types.js","derived/reject.js","derived/symmetricDifference.js","derived/union.js","derived/uniq.js"],"derived/index.js":["derived/addIndex.js","derived/bind.js","derived/chain.js","derived/difference.js","derived/flatten.js","derived/flip.js","derived/ifElse-derivatives.js","derived/isObject.js","derived/j2.js","derived/median.js","derived/pathOr-derivatives.js","derived/pathOr.js","derived/pluck.js","derived/predPass.js","derived/reject.js","derived/symmetricDifference.js","derived/union.js","derived/uniq.js"],"derived/isObject.js":[],"derived/j2.js":[],"derived/median.js":[],"derived/pathOr-derivatives-with-types.js":[],"derived/pathOr-derivatives.js":[],"derived/pathOr.js":[],"derived/pluck.js":[],"derived/predPass-with-types.js":[],"derived/predPass.js":[],"derived/reject.js":[],"derived/symmetricDifference.js":[],"derived/union.js":[],"derived/uniq.js":[],"helpers/arity.js":[],"helpers/iterable.js":[],"helpers/testing.js":[],"quaternary/ifElse.js":[],"quaternary/index-with-types.js":["quaternary/ifElse.js"],"quaternary/index.js":["quaternary/ifElse.js"],"ternary/both.js":[],"ternary/either.js":[],"ternary/index-with-types.js":["ternary/both.js","ternary/either.js","ternary/reduce.js","ternary/slice.js"],"ternary/index.js":["ternary/both.js","ternary/either.js","ternary/reduce.js","ternary/slice.js"],"ternary/reduce.js":[],"ternary/slice.js":[],"types/archetype.js":["types/archetypes.js"],"types/archetypes.js":[],"types/check-params.js":["types/makeChecker.js"],"types/check-return.js":["types/compare.js","types/makeChecker.js"],"types/common.js":["types/ofConstructor.js","types/ofType.js"],"types/compare.js":["types/constructor.js","types/typeof.js","types/union.js"],"types/constructor.js":[],"types/define.js":["types/archetype.js","types/check-params.js","types/check-return.js","types/makeChecker.js","types/system.js"],"types/index.js":["types/archetype.js","types/check-params.js","types/check-return.js","types/common.js","types/compare.js","types/isUnmatched.js","types/makeChecker.js","types/ofConstructor.js","types/ofType.js","types/system.js"],"types/isUnmatched.js":[],"types/makeChecker.js":["types/compare.js","types/memoizer.js"],"types/memoizer.js":["types/symbolToString.js"],"types/ofConstructor.js":[],"types/ofType.js":[],"types/symbolToString.js":[],"types/system.js":[],"types/typeof.js":[],"types/union.js":[]}